.gitignore
README.md
inexactsearchtest.py
setup.py
inexactsearch/__init__.py
inexactsearch/core.py
inexactsearch.egg-info/PKG-INFO
inexactsearch.egg-info/SOURCES.txt
inexactsearch.egg-info/dependency_links.txt
inexactsearch.egg-info/not-zip-safe
inexactsearch.egg-info/requires.txt
inexactsearch.egg-info/top_level.txt
inexactsearch/templates/inexactsearch.html