Metadata-Version: 1.0
Name: inexactsearch
Version: 0.3
Summary: Fuzzy String Search for Indian languages
Home-page: http://silpa.org.in/ApproxSearch
Author: Santhosh Thottingal
Author-email: santhosh.thottingal@gmail.com
License: LGPL-3.0
Platform: UNKNOWN
